LICENSE
MANIFEST.in
README.md
setup.py
rlgym_tools/__init__.py
rlgym_tools/version.py
rlgym_tools.egg-info/PKG-INFO
rlgym_tools.egg-info/SOURCES.txt
rlgym_tools.egg-info/dependency_links.txt
rlgym_tools.egg-info/requires.txt
rlgym_tools.egg-info/top_level.txt
rlgym_tools/rocket_league/__init__.py
rlgym_tools/rocket_league/action_parsers/__init__.py
rlgym_tools/rocket_league/action_parsers/action_history_wrapper.py
rlgym_tools/rocket_league/action_parsers/advanced_lookup_table_action.py
rlgym_tools/rocket_league/action_parsers/delayed_action.py
rlgym_tools/rocket_league/action_parsers/queued_action.py
rlgym_tools/rocket_league/done_conditions/__init__.py
rlgym_tools/rocket_league/done_conditions/ball_hit_ground_condition.py
rlgym_tools/rocket_league/done_conditions/car_on_ground_condition.py
rlgym_tools/rocket_league/done_conditions/game_condition.py
rlgym_tools/rocket_league/math/__init__.py
rlgym_tools/rocket_league/math/ball.py
rlgym_tools/rocket_league/math/gamma.py
rlgym_tools/rocket_league/math/inverse_aerial_controls.py
rlgym_tools/rocket_league/math/relative.py
rlgym_tools/rocket_league/math/skellam.py
rlgym_tools/rocket_league/math/solid_angle.py
rlgym_tools/rocket_league/misc/__init__.py
rlgym_tools/rocket_league/misc/action.py
rlgym_tools/rocket_league/misc/car_bodies.py
rlgym_tools/rocket_league/misc/hitboxes.py
rlgym_tools/rocket_league/misc/serialize.py
rlgym_tools/rocket_league/misc/surface.py
rlgym_tools/rocket_league/obs_builders/__init__.py
rlgym_tools/rocket_league/obs_builders/relative_default_obs.py
rlgym_tools/rocket_league/renderers/__init__.py
rlgym_tools/rocket_league/renderers/rocketsimvis_renderer.py
rlgym_tools/rocket_league/replays/__init__.py
rlgym_tools/rocket_league/replays/carball
rlgym_tools/rocket_league/replays/carball.exe
rlgym_tools/rocket_league/replays/convert.py
rlgym_tools/rocket_league/replays/parsed_replay.py
rlgym_tools/rocket_league/replays/pick_action.py
rlgym_tools/rocket_league/replays/replay_frame.py
rlgym_tools/rocket_league/replays/reward_report.py
rlgym_tools/rocket_league/reward_functions/__init__.py
rlgym_tools/rocket_league/reward_functions/advanced_touch_reward.py
