Metadata-Version: 2.1
Name: rlgym-tools
Version: 2.6.0
Summary: Extra tools for RLGym.
Home-page: https://rlgym.github.io
Author: Rolv-Arild Braaten, Lucas Emery and Matthew Allen
License: Apache 2.0
Keywords: rocket-league,gym,reinforcement-learning
Platform: UNKNOWN
Classifier: Development Status :: 5 - Production/Stable
Classifier: License :: OSI Approved :: Apache Software License
Classifier: Programming Language :: Python :: 3
Classifier: Operating System :: OS Independent
Requires-Python: >=3.7
